infotools/__init__.py
infotools/colortools.py
infotools/datatools.py
infotools/filetools.py
infotools/plottools.py
infotools/spatialtools.py
infotools/tabletools.py
infotools/numbertools/__init__.py
infotools/numbertools/_numbertools.py
infotools/numbertools/_scale.py
infotools/timetools/__init__.py
infotools/timetools/_duration.py
infotools/timetools/_timer.py
infotools/timetools/_timestamp.py
infotools-2025.5.6.dist-info/LICENSE
infotools-2025.5.6.dist-info/METADATA
infotools-2025.5.6.dist-info/WHEEL
infotools-2025.5.6.dist-info/top_level.txt
infotools-2025.5.6.dist-info/RECORD
