Metadata-Version: 2.2
Name: infotools
Version: 2025.5.6
Summary: A collection of tools to make common tasks simpler.
Home-page: https://github.com/Kokitis/infotools
Author: proginoskes
Author-email: chrisdeitrick1@gmail.com
License: MIT
Classifier: Programming Language :: Python :: 3
Classifier: License :: OSI Approved :: MIT License
Classifier: Operating System :: OS Independent
License-File: LICENSE
Requires-Dist: pendulum
Requires-Dist: fuzzywuzzy
Requires-Dist: loguru
Requires-Dist: psutil
Requires-Dist: pandas
Requires-Dist: tqdm
Dynamic: author
Dynamic: author-email
Dynamic: classifier
Dynamic: home-page
Dynamic: license
Dynamic: requires-dist
Dynamic: summary
